{
  "_class": "rectangle",
  "booleanOperation": -1,
  "clippingMaskMode": 0,
  "do_objectID": "CE2AFBEF-54B9-4679-A539-23AEA46F9E50",
  "edited": false,
  "exportOptions": {
    "_class": "exportOptions",
    "do_objectID": "6D63B26E-270D-4F47-97D8-1F9DE0B50E47",
    "exportFormats": [
      {
        "_class": "exportFormat",
        "absoluteSize": 0,
        "fileFormat": "png",
        "name": "",
        "namingScheme": 0,
        "scale": 1,
        "visibleScaleType": 0
      }
    ],
    "includedLayerIds": [
    ],
    "layerOptions": 0,
    "shouldTrim": false
  },
  "fixedRadius": 2.883845126835781,
  "frame": {
    "_class": "rect",
    "constrainProportions": false,
    "do_objectID": "5542B8A8-5ED1-471F-A82F-F8807F17C4FE",
    "height": 89.87983978638184,
    "width": 360,
    "x": 0,
    "y": 0
  },
  "hasClippingMask": false,
  "hasConvertedToNewRoundCorners": true,
  "isClosed": true,
  "isFixedToViewport": false,
  "isFlippedHorizontal": false,
  "isFlippedVertical": false,
  "isLocked": false,
  "isVisible": true,
  "layerListExpandedType": 1,
  "name": "bg-box",
  "nameIsFixed": true,
  "pointRadiusBehaviour": 0,
  "points": [
    {
      "_class": "curvePoint",
      "cornerRadius": 2.883845126835781,
      "curveFrom": "{0, 0}",
      "curveMode": 1,
      "curveTo": "{0, 0}",
      "hasCurveFrom": false,
      "hasCurveTo": false,
      "point": "{0, 0}"
    },
    {
      "_class": "curvePoint",
      "cornerRadius": 2.883845126835781,
      "curveFrom": "{1, 0}",
      "curveMode": 1,
      "curveTo": "{1, 0}",
      "hasCurveFrom": false,
      "hasCurveTo": false,
      "point": "{1, 0}"
    },
    {
      "_class": "curvePoint",
      "cornerRadius": 2.883845126835781,
      "curveFrom": "{1, 1}",
      "curveMode": 1,
      "curveTo": "{1, 1}",
      "hasCurveFrom": false,
      "hasCurveTo": false,
      "point": "{1, 1}"
    },
    {
      "_class": "curvePoint",
      "cornerRadius": 2.883845126835781,
      "curveFrom": "{0, 1}",
      "curveMode": 1,
      "curveTo": "{0, 1}",
      "hasCurveFrom": false,
      "hasCurveTo": false,
      "point": "{0, 1}"
    }
  ],
  "resizingConstraint": 63,
  "resizingType": 0,
  "rotation": 0,
  "shouldBreakMaskChain": false,
  "style": {
    "_class": "style",
    "blur": {
      "_class": "blur",
      "center": "{0.5, 0.5}",
      "do_objectID": "CC3FE34A-FE1E-4AE7-B488-FC9E421CFAC5",
      "isEnabled": false,
      "motionAngle": 0,
      "radius": 2.403204272363151,
      "saturation": 1,
      "type": 0
    },
    "borders": [
      {
        "_class": "border",
        "color": {
          "_class": "color",
          "alpha": 1,
          "blue": 0.8392156862745098,
          "green": 0.8392156862745098,
          "red": 0.8392156862745098
        },
        "fillType": 0,
        "isEnabled": true,
        "position": 1,
        "thickness": 1.44192256341789
      }
    ],
    "do_objectID": "D7134082-9619-4C3B-9CFA-CF8BA99216DD",
    "endMarkerType": 0,
    "fills": [
      {
        "_class": "fill",
        "color": {
          "_class": "color",
          "alpha": 1,
          "blue": 0.9803921568627451,
          "green": 0.9803921568627451,
          "red": 0.9803921568627451
        },
        "fillType": 0,
        "isEnabled": true,
        "noiseIndex": 0,
        "noiseIntensity": 0,
        "patternFillType": 0,
        "patternTileScale": 1
      }
    ],
    "miterLimit": 10,
    "shadows": [
      {
        "_class": "shadow",
        "blurRadius": 3,
        "color": {
          "_class": "color",
          "alpha": 0.1011379076086956,
          "blue": 0,
          "green": 0,
          "red": 0
        },
        "contextSettings": {
          "_class": "graphicsContextSettings",
          "blendMode": 0,
          "opacity": 1
        },
        "isEnabled": true,
        "offsetX": 0,
        "offsetY": 1,
        "spread": 0
      }
    ],
    "startMarkerType": 0,
    "windingRule": 1
  }
}