{
  "_class": "group",
  "booleanOperation": -1,
  "clippingMaskMode": 0,
  "do_objectID": "B312BCE8-9825-4B1E-8341-5C4A30D6B94C",
  "exportOptions": {
    "_class": "exportOptions",
    "exportFormats": [
    ],
    "includedLayerIds": [
    ],
    "layerOptions": 0,
    "shouldTrim": false
  },
  "frame": {
    "_class": "rect",
    "constrainProportions": false,
    "do_objectID": "10D57910-F7FA-4063-A50A-CF2345BBAAC7",
    "height": 242,
    "width": 95,
    "x": 500,
    "y": 62
  },
  "hasClickThrough": false,
  "hasClippingMask": false,
  "isFixedToViewport": false,
  "isFlippedHorizontal": false,
  "isFlippedVertical": false,
  "isLocked": false,
  "isVisible": true,
  "layerListExpandedType": 0,
  "layers": [
    {
      "class": "text",
      "id": "306B72DF-A196-4CC6-B0C3-A4957B62F006"
    },
    {
      "class": "text",
      "id": "71ECA9F2-6E95-4439-B4EE-47D09D6B1462"
    },
    {
      "class": "text",
      "id": "88385544-653C-4783-B404-02488584F8DF"
    },
    {
      "class": "text",
      "id": "A86E98D3-7774-4012-AFEB-222B9C439E51"
    },
    {
      "class": "text",
      "id": "4C2AEFA0-0173-4E3C-9B9B-F322E30ED068"
    }
  ],
  "name": "Group",
  "nameIsFixed": false,
  "resizingConstraint": 63,
  "resizingType": 0,
  "rotation": 0,
  "shouldBreakMaskChain": false,
  "style": {
    "_class": "style",
    "do_objectID": "2E2A9357-DD1E-4A6D-BA57-CB0ABE784316",
    "endMarkerType": 0,
    "miterLimit": 10,
    "startMarkerType": 0,
    "windingRule": 1
  },
  "userInfo": {
    "com.animaapp.stc-sketch-plugin": {
      "kModelPropertiesKey": {
      }
    }
  }
}