{
  "_class": "shapePath",
  "booleanOperation": -1,
  "clippingMaskMode": 0,
  "do_objectID": "0CB8183B-DF2C-4B4B-9D5E-A671D1533CA7",
  "edited": true,
  "exportOptions": {
    "_class": "exportOptions",
    "exportFormats": [
    ],
    "includedLayerIds": [
    ],
    "layerOptions": 0,
    "shouldTrim": false
  },
  "frame": {
    "_class": "rect",
    "constrainProportions": false,
    "do_objectID": "978115CC-D8AF-466E-9B1B-316C9D47A029",
    "height": 9.8056640625,
    "width": 8.674440703706553,
    "x": 5.35114709649865,
    "y": 4.6875
  },
  "hasClippingMask": false,
  "isClosed": true,
  "isFixedToViewport": false,
  "isFlippedHorizontal": false,
  "isFlippedVertical": false,
  "isLocked": false,
  "isVisible": true,
  "layerListExpandedType": 0,
  "name": "Path",
  "nameIsFixed": false,
  "pointRadiusBehaviour": 1,
  "points": [
    {
      "_class": "curvePoint",
      "cornerRadius": 0,
      "curveFrom": "{0.35579848994558955, 0.047804003585300271}",
      "curveMode": 4,
      "curveTo": "{0.35579848994558955, 0.021511801613385145}",
      "hasCurveFrom": false,
      "hasCurveTo": true,
      "point": "{0.35579848994558955, 0.047804003585300271}"
    },
    {
      "_class": "curvePoint",
      "cornerRadius": 0,
      "curveFrom": "{0.35579848994558955, 0.50990937157653626}",
      "curveMode": 1,
      "curveTo": "{0.35579848994558955, 0.50990937157653626}",
      "hasCurveFrom": false,
      "hasCurveTo": false,
      "point": "{0.35579848994558955, 0.50990937157653626}"
    },
    {
      "_class": "curvePoint",
      "cornerRadius": 0,
      "curveFrom": "{0.0059020120432056889, 0.50990937157653626}",
      "curveMode": 4,
      "curveTo": "{0.054085954302607278, 0.50990937157653626}",
      "hasCurveFrom": true,
      "hasCurveTo": false,
      "point": "{0.054085954302607278, 0.50990937157653626}"
    },
    {
      "_class": "curvePoint",
      "cornerRadius": 0,
      "curveFrom": "{0.015808990825512518, 0.59157454436809087}",
      "curveMode": 4,
      "curveTo": "{-0.017964800477806391, 0.56129867543073397}",
      "hasCurveFrom": false,
      "hasCurveTo": true,
      "point": "{0.015808990825512518, 0.59157454436809087}"
    },
    {
      "_class": "curvePoint",
      "cornerRadius": 0,
      "curveFrom": "{0.48278794524606855, 1.0046808086843941}",
      "curveMode": 4,
      "curveTo": "{0.46162303602932209, 0.98595757394681816}",
      "hasCurveFrom": true,
      "hasCurveTo": false,
      "point": "{0.46162303602932209, 0.98595757394681816}"
    },
    {
      "_class": "curvePoint",
      "cornerRadius": 0,
      "curveFrom": "{0.53817696298351159, 0.98595757394681816}",
      "curveMode": 4,
      "curveTo": "{0.51701205376676518, 1.0046808086843941}",
      "hasCurveFrom": false,
      "hasCurveTo": true,
      "point": "{0.53817696298351159, 0.98595757394681816}"
    },
    {
      "_class": "curvePoint",
      "cornerRadius": 0,
      "curveFrom": "{1.0182151167080178, 0.56129867543073397}",
      "curveMode": 4,
      "curveTo": "{0.98399100818732121, 0.59157454436809087}",
      "hasCurveFrom": true,
      "hasCurveTo": false,
      "point": "{0.98399100818732121, 0.59157454436809087}"
    },
    {
      "_class": "curvePoint",
      "cornerRadius": 0,
      "curveFrom": "{0.94571404471022646, 0.50990937157653626}",
      "curveMode": 4,
      "curveTo": "{0.99389798696962806, 0.50990937157653626}",
      "hasCurveFrom": false,
      "hasCurveTo": true,
      "point": "{0.94571404471022646, 0.50990937157653626}"
    },
    {
      "_class": "curvePoint",
      "cornerRadius": 0,
      "curveFrom": "{0.64400150906724418, 0.50990937157653626}",
      "curveMode": 1,
      "curveTo": "{0.64400150906724418, 0.50990937157653626}",
      "hasCurveFrom": false,
      "hasCurveTo": false,
      "point": "{0.64400150906724418, 0.50990937157653626}"
    },
    {
      "_class": "curvePoint",
      "cornerRadius": 0,
      "curveFrom": "{0.64400150906724418, 0.021511801613385145}",
      "curveMode": 4,
      "curveTo": "{0.64400150906724418, 0.047804003585300271}",
      "hasCurveFrom": true,
      "hasCurveTo": false,
      "point": "{0.64400150906724418, 0.047804003585300271}"
    },
    {
      "_class": "curvePoint",
      "cornerRadius": 0,
      "curveFrom": "{0.58996344298193393, 0}",
      "curveMode": 4,
      "curveTo": "{0.61968437932885467, 0}",
      "hasCurveFrom": false,
      "hasCurveTo": true,
      "point": "{0.58996344298193393, 0}"
    },
    {
      "_class": "curvePoint",
      "cornerRadius": 0,
      "curveFrom": "{0.38011561968397917, 0}",
      "curveMode": 4,
      "curveTo": "{0.4098365560308998, 0}",
      "hasCurveFrom": true,
      "hasCurveTo": false,
      "point": "{0.4098365560308998, 0}"
    }
  ],
  "resizingConstraint": 63,
  "resizingType": 0,
  "rotation": 0,
  "shouldBreakMaskChain": false,
  "style": {
    "_class": "style",
    "do_objectID": "E2E472B9-A8B3-48D6-8CDC-44CDCFA188EB",
    "endMarkerType": 0,
    "fills": [
      {
        "_class": "fill",
        "color": {
          "_class": "color",
          "alpha": 1,
          "blue": 0,
          "green": 0,
          "red": 0
        },
        "fillType": 0,
        "isEnabled": true,
        "noiseIndex": 0,
        "noiseIntensity": 0,
        "patternFillType": 1,
        "patternTileScale": 1
      }
    ],
    "miterLimit": 10,
    "startMarkerType": 0,
    "windingRule": 0
  }
}