{
  "_class": "group",
  "booleanOperation": 0,
  "clippingMaskMode": 0,
  "do_objectID": "23FCA41D-DC89-4708-A14F-9DB1CB174BFF",
  "exportOptions": {
    "_class": "exportOptions",
    "exportFormats": [
    ],
    "includedLayerIds": [
    ],
    "layerOptions": 0,
    "shouldTrim": false
  },
  "frame": {
    "_class": "rect",
    "constrainProportions": false,
    "do_objectID": "8981EEA5-7F57-4552-9900-551AAB0496DF",
    "height": 76,
    "width": 285,
    "x": 0,
    "y": 0
  },
  "hasClickThrough": false,
  "hasClippingMask": false,
  "isFixedToViewport": false,
  "isFlippedHorizontal": false,
  "isFlippedVertical": false,
  "isLocked": false,
  "isVisible": true,
  "layerListExpandedType": 0,
  "layers": [
    {
      "class": "symbolInstance",
      "id": "B21F8266-80FD-4F67-BB4D-FA47D6D1C85B"
    },
    {
      "class": "text",
      "id": "7973CB00-5E01-445E-A658-56B846F602B5"
    }
  ],
  "name": "Default",
  "nameIsFixed": true,
  "resizingConstraint": 63,
  "resizingType": 0,
  "rotation": 0,
  "shouldBreakMaskChain": false,
  "style": {
    "_class": "style",
    "do_objectID": "83179C8E-BD16-4679-9FD6-CC013F160BCD",
    "endMarkerType": 0,
    "miterLimit": 10,
    "startMarkerType": 0,
    "windingRule": 1
  }
}