{
  "_class": "group",
  "booleanOperation": -1,
  "clippingMaskMode": 0,
  "do_objectID": "B2858AFB-7C40-4A48-ACFA-C223305DB31B",
  "exportOptions": {
    "_class": "exportOptions",
    "exportFormats": [
    ],
    "includedLayerIds": [
    ],
    "layerOptions": 0,
    "shouldTrim": false
  },
  "frame": {
    "_class": "rect",
    "constrainProportions": false,
    "do_objectID": "997D491A-31B3-4FAD-A37C-1D93E04735C6",
    "height": 98,
    "width": 97.99999999999994,
    "x": 0.9999999999999994,
    "y": 0
  },
  "hasClickThrough": false,
  "hasClippingMask": false,
  "isFixedToViewport": false,
  "isFlippedHorizontal": false,
  "isFlippedVertical": false,
  "isLocked": false,
  "isVisible": true,
  "layerListExpandedType": 2,
  "layers": [
    {
      "class": "rectangle",
      "id": "6F55A3D5-F078-4FAE-B2CD-88164D345ED1"
    },
    {
      "class": "bitmap",
      "id": "27CC0E64-DC38-4FDB-BEE0-849BDA4F0A07"
    }
  ],
  "name": "Group 7",
  "nameIsFixed": false,
  "resizingConstraint": 63,
  "resizingType": 0,
  "rotation": 0,
  "shouldBreakMaskChain": false,
  "style": {
    "_class": "style",
    "do_objectID": "696EEBE5-3AA2-4DB1-A3AE-473ACE2E1F28",
    "endMarkerType": 0,
    "miterLimit": 10,
    "startMarkerType": 0,
    "windingRule": 1
  }
}