{
  "_class": "artboard",
  "backgroundColor": {
    "_class": "color",
    "alpha": 1,
    "blue": 0.9490196078431372,
    "do_objectID": "4C698D00-DAE4-49FD-A4B7-8DE87727A1D7",
    "green": 0.9529411764705882,
    "red": 0.9568627450980393
  },
  "booleanOperation": -1,
  "clippingMaskMode": 0,
  "do_objectID": "D2617F66-946F-456A-84A8-84253AD84874",
  "exportOptions": {
    "_class": "exportOptions",
    "do_objectID": "9777284C-1145-43BF-A9A9-2B63DF55E808",
    "exportFormats": [
    ],
    "includedLayerIds": [
    ],
    "layerOptions": 0,
    "shouldTrim": false
  },
  "frame": {
    "_class": "rect",
    "constrainProportions": false,
    "do_objectID": "1964C180-F7E8-4606-9145-3B23461336E0",
    "height": 3766,
    "width": 375,
    "x": 1317,
    "y": -3128
  },
  "hasBackgroundColor": false,
  "hasClickThrough": false,
  "hasClippingMask": false,
  "horizontalRulerData": {
    "_class": "rulerData",
    "base": 0,
    "do_objectID": "598ED0E0-52D5-4FDF-AF99-684C38F9FC79",
    "guides": [
      341,
      37
    ]
  },
  "includeBackgroundColorInExport": true,
  "includeInCloudUpload": true,
  "isFixedToViewport": false,
  "isFlippedHorizontal": false,
  "isFlippedVertical": false,
  "isFlowHome": false,
  "isLocked": false,
  "isVisible": true,
  "layerListExpandedType": 2,
  "layers": [
    {
      "class": "group",
      "id": "3B4C65DF-8527-49A9-B83C-EDDBAB49CA9A"
    },
    {
      "class": "group",
      "id": "B59609AC-5A1B-41A5-8CE1-5DD4A0324833"
    },
    {
      "class": "rectangle",
      "id": "156E1E6C-55E0-4AB8-BB8F-3A83E91C4548"
    },
    {
      "class": "rectangle",
      "id": "9C196BFC-8CC6-490B-A154-D969E2933F0D"
    },
    {
      "class": "bitmap",
      "id": "5143C6E7-6950-4D2E-AD30-A568C4431047"
    },
    {
      "class": "symbolInstance",
      "id": "092777B5-767C-4970-900F-DF58E3807D4A"
    },
    {
      "class": "rectangle",
      "id": "32DD7D88-D635-4166-AAD7-CFC2B8FD8AB7"
    },
    {
      "class": "text",
      "id": "5EC94E7B-F043-40BF-AC9F-F7AE21F74497"
    },
    {
      "class": "group",
      "id": "578406E5-1DB8-4E7F-9FD0-92681B2E1394"
    },
    {
      "class": "group",
      "id": "BC28246D-AB8C-4B5F-A9BE-C78A9CE7315C"
    },
    {
      "class": "text",
      "id": "2D432659-9050-41BB-BE61-72520AD88B2A"
    },
    {
      "class": "text",
      "id": "82441C49-A8CC-45B7-B958-A79F1A7B4FAC"
    },
    {
      "class": "group",
      "id": "A0BBB7F8-3626-418E-B5D4-5A3E47E0AC63"
    },
    {
      "class": "text",
      "id": "2D1FBA10-8673-411B-8D64-B4056C0F3A53"
    },
    {
      "class": "text",
      "id": "027B3F73-FD36-4618-ACC0-65F5A8A79E52"
    }
  ],
  "name": "PRODUCTO Plantilla 8 ",
  "nameIsFixed": true,
  "presetDictionary": {
    "allowResizedMatching": 1,
    "height": 667,
    "name": "iPhone 8",
    "offersLandscapeVariant": 1,
    "width": 375
  },
  "resizesContent": false,
  "resizingConstraint": 63,
  "resizingType": 0,
  "rotation": 0,
  "shouldBreakMaskChain": true,
  "style": {
    "_class": "style",
    "do_objectID": "C76D1F8E-646F-4E0C-927A-FE1D77A0DEE9",
    "endMarkerType": 0,
    "miterLimit": 10,
    "startMarkerType": 0,
    "windingRule": 1
  },
  "verticalRulerData": {
    "_class": "rulerData",
    "base": 0,
    "do_objectID": "EBE94944-BB22-40AE-8BD6-0948A3CA4DDB",
    "guides": [
    ]
  }
}