{
  "_class": "shapePath",
  "booleanOperation": -1,
  "clippingMaskMode": 0,
  "do_objectID": "C41AD2F3-3D73-452F-A6A6-3EA898E9410E",
  "edited": true,
  "exportOptions": {
    "_class": "exportOptions",
    "exportFormats": [
    ],
    "includedLayerIds": [
    ],
    "layerOptions": 0,
    "shouldTrim": false
  },
  "frame": {
    "_class": "rect",
    "constrainProportions": false,
    "do_objectID": "3490C6DB-53C8-4081-A31E-317173596339",
    "height": 4.999999999999996,
    "width": 3.490524146160184,
    "x": 0.04342116633980453,
    "y": 12.49996093749996
  },
  "hasClippingMask": false,
  "isClosed": true,
  "isFixedToViewport": false,
  "isFlippedHorizontal": false,
  "isFlippedVertical": false,
  "isLocked": false,
  "isVisible": true,
  "layerListExpandedType": 0,
  "name": "Path",
  "nameIsFixed": false,
  "pointRadiusBehaviour": 1,
  "points": [
    {
      "_class": "curvePoint",
      "cornerRadius": 0,
      "curveFrom": "{0.026102121012516445, 0.8016484375000007}",
      "curveMode": 1,
      "curveTo": "{0.026102121012516445, 0.8016484375000007}",
      "hasCurveFrom": false,
      "hasCurveTo": false,
      "point": "{0.026102121012516445, 0.8016484375000007}"
    },
    {
      "_class": "curvePoint",
      "cornerRadius": 0,
      "curveFrom": "{0.13192433697006478, 0.67716406250000094}",
      "curveMode": 4,
      "curveTo": "{0.088805365091423311, 0.72914843750000091}",
      "hasCurveFrom": true,
      "hasCurveTo": false,
      "point": "{0.088805365091423311, 0.72914843750000091}"
    },
    {
      "_class": "curvePoint",
      "cornerRadius": 0,
      "curveFrom": "{0.31807564198675886, 0.72093750000000101}",
      "curveMode": 4,
      "curveTo": "{0.19069953559623273, 0.67442968750000076}",
      "hasCurveFrom": true,
      "hasCurveTo": true,
      "point": "{0.26320610678795814, 0.70452343750000102}"
    },
    {
      "_class": "curvePoint",
      "cornerRadius": 0,
      "curveFrom": "{0.53754259176927588, 0.72914843750000091}",
      "curveMode": 3,
      "curveTo": "{0.37097555895284717, 0.72914843750000091}",
      "hasCurveFrom": true,
      "hasCurveTo": true,
      "point": "{0.42389785794430723, 0.72914843750000091}"
    },
    {
      "_class": "curvePoint",
      "cornerRadius": 0,
      "curveFrom": "{0.5845784180879704, 0.61286718750000069}",
      "curveMode": 3,
      "curveTo": "{0.5845784180879704, 0.70178906250000084}",
      "hasCurveFrom": true,
      "hasCurveTo": true,
      "point": "{0.5845784180879704, 0.66485156250000077}"
    },
    {
      "_class": "curvePoint",
      "cornerRadius": 0,
      "curveFrom": "{0.40626082195138258, 0.5937109375000007}",
      "curveMode": 4,
      "curveTo": "{0.52186398299637771, 0.5937109375000007}",
      "hasCurveFrom": false,
      "hasCurveTo": true,
      "point": "{0.40626082195138258, 0.5937109375000007}"
    },
    {
      "_class": "curvePoint",
      "cornerRadius": 0,
      "curveFrom": "{0.28671842444096257, 0.5937109375000007}",
      "curveMode": 4,
      "curveTo": "{0.35334971397260839, 0.5937109375000007}",
      "hasCurveFrom": true,
      "hasCurveTo": false,
      "point": "{0.35334971397260839, 0.5937109375000007}"
    },
    {
      "_class": "curvePoint",
      "cornerRadius": 0,
      "curveFrom": "{0.21617028046926373, 0.53214843750000074}",
      "curveMode": 4,
      "curveTo": "{0.24949711624777243, 0.57729687500000071}",
      "hasCurveFrom": false,
      "hasCurveTo": true,
      "point": "{0.21617028046926373, 0.53214843750000074}"
    },
    {
      "_class": "curvePoint",
      "cornerRadius": 0,
      "curveFrom": "{0.176990545056047, 0.48016406250000077}",
      "curveMode": 4,
      "curveTo": "{0.20441971714910442, 0.51710156250000083}",
      "hasCurveFrom": true,
      "hasCurveTo": false,
      "point": "{0.20441971714910442, 0.51710156250000083}"
    },
    {
      "_class": "curvePoint",
      "cornerRadius": 0,
      "curveFrom": "{0.23576574368221495, 0.40082031250000066}",
      "curveMode": 4,
      "curveTo": "{0.19069953559623279, 0.44049218750000096}",
      "hasCurveFrom": false,
      "hasCurveTo": true,
      "point": "{0.23576574368221495, 0.40082031250000066}"
    },
    {
      "_class": "curvePoint",
      "cornerRadius": 0,
      "curveFrom": "{0.37490360440558618, 0.28043750000000067}",
      "curveMode": 4,
      "curveTo": "{0.29848017877380767, 0.34610156250000051}",
      "hasCurveFrom": true,
      "hasCurveTo": false,
      "point": "{0.29848017877380767, 0.34610156250000051}"
    },
    {
      "_class": "curvePoint",
      "cornerRadius": 0,
      "curveFrom": "{0.43564842126446651, 0.24076562500000043}",
      "curveMode": 4,
      "curveTo": "{0.43564842126446651, 0.24076562500000043}",
      "hasCurveFrom": false,
      "hasCurveTo": true,
      "point": "{0.43564842126446651, 0.24076562500000043}"
    },
    {
      "_class": "curvePoint",
      "cornerRadius": 0,
      "curveFrom": "{0.43564842126446651, 0.23803125000000025}",
      "curveMode": 4,
      "curveTo": "{0.43564842126446651, 0.23803125000000025}",
      "hasCurveFrom": true,
      "hasCurveTo": false,
      "point": "{0.43564842126446651, 0.23803125000000025}"
    },
    {
      "_class": "curvePoint",
      "cornerRadius": 0,
      "curveFrom": "{0.29455213332106878, 0.24624218750000015}",
      "curveMode": 4,
      "curveTo": "{0.38861259494577194, 0.24624218750000015}",
      "hasCurveFrom": false,
      "hasCurveTo": true,
      "point": "{0.29455213332106878, 0.24624218750000015}"
    },
    {
      "_class": "curvePoint",
      "cornerRadius": 0,
      "curveFrom": "{0.065281856425733073, 0.24624218750000015}",
      "curveMode": 4,
      "curveTo": "{0.14955018195030362, 0.24624218750000015}",
      "hasCurveFrom": true,
      "hasCurveTo": false,
      "point": "{0.14955018195030362, 0.24624218750000015}"
    },
    {
      "_class": "curvePoint",
      "cornerRadius": 0,
      "curveFrom": "{0.02216288454709163, 0.15732031250000009}",
      "curveMode": 4,
      "curveTo": "{0.02216288454709163, 0.21477343749999997}",
      "hasCurveFrom": false,
      "hasCurveTo": true,
      "point": "{0.02216288454709163, 0.15732031250000009}"
    },
    {
      "_class": "curvePoint",
      "cornerRadius": 0,
      "curveFrom": "{0.02216288454709163, 0.030093750000000266}",
      "curveMode": 4,
      "curveTo": "{0.02216288454709163, 0.088921875000000081}",
      "hasCurveFrom": true,
      "hasCurveTo": false,
      "point": "{0.02216288454709163, 0.088921875000000081}"
    },
    {
      "_class": "curvePoint",
      "cornerRadius": 0,
      "curveFrom": "{0.14955018195030362, 0}",
      "curveMode": 4,
      "curveTo": "{0.065281856425733101, 0}",
      "hasCurveFrom": false,
      "hasCurveTo": true,
      "point": "{0.14955018195030362, 0}"
    },
    {
      "_class": "curvePoint",
      "cornerRadius": 0,
      "curveFrom": "{0.88830250238237196, 0}",
      "curveMode": 4,
      "curveTo": "{0.8040453678704873, 0}",
      "hasCurveFrom": true,
      "hasCurveTo": false,
      "point": "{0.8040453678704873, 0}"
    },
    {
      "_class": "curvePoint",
      "cornerRadius": 0,
      "curveFrom": "{0.93142147426101352, 0.088921875000000081}",
      "curveMode": 4,
      "curveTo": "{0.93142147426101352, 0.031460937499999911}",
      "hasCurveFrom": false,
      "hasCurveTo": true,
      "point": "{0.93142147426101352, 0.088921875000000081}"
    },
    {
      "_class": "curvePoint",
      "cornerRadius": 0,
      "curveFrom": "{0.93142147426101352, 0.16005468750000026}",
      "curveMode": 4,
      "curveTo": "{0.93142147426101352, 0.11491406250000008}",
      "hasCurveFrom": true,
      "hasCurveTo": false,
      "point": "{0.93142147426101352, 0.11491406250000008}"
    },
    {
      "_class": "curvePoint",
      "cornerRadius": 0,
      "curveFrom": "{0.87458232082950049, 0.22571875000000008}",
      "curveMode": 4,
      "curveTo": "{0.91574286548811534, 0.19152343749999998}",
      "hasCurveFrom": false,
      "hasCurveTo": true,
      "point": "{0.87458232082950049, 0.22571875000000008}"
    },
    {
      "_class": "curvePoint",
      "cornerRadius": 0,
      "curveFrom": "{0.89810582949519069, 0.42271093749999994}",
      "curveMode": 4,
      "curveTo": "{0.67863887971267367, 0.38303906250000014}",
      "hasCurveFrom": true,
      "hasCurveTo": false,
      "point": "{0.67863887971267367, 0.38303906250000014}"
    },
    {
      "_class": "curvePoint",
      "cornerRadius": 0,
      "curveFrom": "{1, 0.82216406250000007}",
      "curveMode": 3,
      "curveTo": "{1, 0.54309375000000037}",
      "hasCurveFrom": true,
      "hasCurveTo": true,
      "point": "{1, 0.65526562500000007}"
    },
    {
      "_class": "curvePoint",
      "cornerRadius": 0,
      "curveFrom": "{0.27102862465537847, 1}",
      "curveMode": 3,
      "curveTo": "{0.83931943985633672, 1}",
      "hasCurveFrom": true,
      "hasCurveTo": true,
      "point": "{0.45720231169744424, 1}"
    },
    {
      "_class": "curvePoint",
      "cornerRadius": 0,
      "curveFrom": "{-0.0091831419860188539, 0.89330468750000014}",
      "curveMode": 4,
      "curveTo": "{0.14170528205751162, 0.96306249999999993}",
      "hasCurveFrom": true,
      "hasCurveTo": true,
      "point": "{0.055489720325600421, 0.92613281250000012}"
    },
    {
      "_class": "curvePoint",
      "cornerRadius": 0,
      "curveFrom": "{0.026102121012516466, 0.80164843749999981}",
      "curveMode": 4,
      "curveTo": "{-0.015058423646098476, 0.84953124999999996}",
      "hasCurveFrom": false,
      "hasCurveTo": true,
      "point": "{0.026102121012516466, 0.80164843749999981}"
    }
  ],
  "resizingConstraint": 63,
  "resizingType": 0,
  "rotation": 0,
  "shouldBreakMaskChain": false,
  "style": {
    "_class": "style",
    "do_objectID": "57B3731B-852B-41A9-AE0B-1E4399A92814",
    "endMarkerType": 0,
    "fills": [
      {
        "_class": "fill",
        "color": {
          "_class": "color",
          "alpha": 1,
          "blue": 0,
          "green": 0,
          "red": 0
        },
        "fillType": 0,
        "isEnabled": true,
        "noiseIndex": 0,
        "noiseIntensity": 0,
        "patternFillType": 1,
        "patternTileScale": 1
      }
    ],
    "miterLimit": 10,
    "startMarkerType": 0,
    "windingRule": 0
  }
}