{
  "_class": "shapePath",
  "booleanOperation": -1,
  "clippingMaskMode": 0,
  "do_objectID": "AED953D2-1D34-49CC-9F28-81E587042D15",
  "edited": true,
  "exportOptions": {
    "_class": "exportOptions",
    "exportFormats": [
    ],
    "includedLayerIds": [
    ],
    "layerOptions": 0,
    "shouldTrim": false
  },
  "frame": {
    "_class": "rect",
    "constrainProportions": false,
    "do_objectID": "F36BC54B-A92D-4C14-AC81-1B784B13E467",
    "height": 10.9753125,
    "width": 9.688701498844884,
    "x": 4.328203125000002,
    "y": 4.193906250000055
  },
  "hasClippingMask": false,
  "isClosed": true,
  "isFixedToViewport": false,
  "isFlippedHorizontal": false,
  "isFlippedVertical": false,
  "isLocked": false,
  "isVisible": true,
  "layerListExpandedType": 0,
  "name": "Path",
  "nameIsFixed": false,
  "pointRadiusBehaviour": 1,
  "points": [
    {
      "_class": "curvePoint",
      "cornerRadius": 0,
      "curveFrom": "{0.94720107112332119, 0.88723270977477853}",
      "curveMode": 4,
      "curveTo": "{0.98596239275602637, 0.85266649582870646}",
      "hasCurveFrom": true,
      "hasCurveTo": false,
      "point": "{0.98596239275602637, 0.85266649582870646}"
    },
    {
      "_class": "curvePoint",
      "cornerRadius": 0,
      "curveFrom": "{0.23405968026472548, 1}",
      "curveMode": 3,
      "curveTo": "{0.80239644997081006, 1}",
      "hasCurveFrom": true,
      "hasCurveTo": true,
      "point": "{0.56639749409704232, 1}"
    },
    {
      "_class": "curvePoint",
      "cornerRadius": 0,
      "curveFrom": "{0, 0.21443367216195447}",
      "curveMode": 2,
      "curveTo": "{0, 0.78138079781327408}",
      "hasCurveFrom": true,
      "hasCurveTo": true,
      "point": "{0, 0.49614546852310581}"
    },
    {
      "_class": "curvePoint",
      "cornerRadius": 0,
      "curveFrom": "{0.78737411957727332, 0}",
      "curveMode": 3,
      "curveTo": "{0.24301421483371222, 0}",
      "hasCurveFrom": true,
      "hasCurveTo": true,
      "point": "{0.56348656480446746, 0}"
    },
    {
      "_class": "curvePoint",
      "cornerRadius": 0,
      "curveFrom": "{0.97427977602620353, 0.13784616361465754}",
      "curveMode": 3,
      "curveTo": "{0.92125670824559491, 0.094743885424674712}",
      "hasCurveFrom": true,
      "hasCurveTo": true,
      "point": "{0.95695792553887604, 0.12378277953361234}"
    },
    {
      "_class": "curvePoint",
      "cornerRadius": 0,
      "curveFrom": "{0.96476340907132008, 0.17831568007744653}",
      "curveMode": 4,
      "curveTo": "{0.97757823345014738, 0.1608907898572651}",
      "hasCurveFrom": false,
      "hasCurveTo": true,
      "point": "{0.96476340907132008, 0.17831568007744653}"
    },
    {
      "_class": "curvePoint",
      "cornerRadius": 0,
      "curveFrom": "{0.87608085959836568, 0.2995501267048204}",
      "curveMode": 4,
      "curveTo": "{0.89156684216454218, 0.27837333788901225}",
      "hasCurveFrom": true,
      "hasCurveTo": false,
      "point": "{0.89156684216454218, 0.27837333788901225}"
    },
    {
      "_class": "curvePoint",
      "cornerRadius": 0,
      "curveFrom": "{0.78636214831351114, 0.26465291421087089}",
      "curveMode": 3,
      "curveTo": "{0.8433228256618428, 0.30429088010022493}",
      "hasCurveFrom": true,
      "hasCurveTo": true,
      "point": "{0.8210151085208236, 0.28876953959169721}"
    },
    {
      "_class": "curvePoint",
      "cornerRadius": 0,
      "curveFrom": "{0.37747737665733955, 0.20855399903191815}",
      "curveMode": 3,
      "curveTo": "{0.69274875877848063, 0.20855399903191815}",
      "hasCurveFrom": true,
      "hasCurveTo": true,
      "point": "{0.5722233844402147, 0.20855399903191815}"
    },
    {
      "_class": "curvePoint",
      "cornerRadius": 0,
      "curveFrom": "{0.2580849263235242, 0.64159619600808615}",
      "curveMode": 3,
      "curveTo": "{0.2580849263235242, 0.3342978559835994}",
      "hasCurveFrom": true,
      "hasCurveTo": true,
      "point": "{0.2580849263235242, 0.49357578087184295}"
    },
    {
      "_class": "curvePoint",
      "cornerRadius": 0,
      "curveFrom": "{0.70534397084219724, 0.79144600096808171}",
      "curveMode": 3,
      "curveTo": "{0.36649083604478266, 0.79144600096808171}",
      "hasCurveFrom": true,
      "hasCurveTo": true,
      "point": "{0.57367884908650202, 0.79144600096808171}"
    },
    {
      "_class": "curvePoint",
      "cornerRadius": 0,
      "curveFrom": "{0.85991754168433232, 0.67726217932291188}",
      "curveMode": 3,
      "curveTo": "{0.80285607038542706, 0.72368383588166618}",
      "hasCurveFrom": true,
      "hasCurveTo": true,
      "point": "{0.83867017690335088, 0.69454884542011885}"
    },
    {
      "_class": "curvePoint",
      "cornerRadius": 0,
      "curveFrom": "{0.91051610487243839, 0.70073460322883729}",
      "curveMode": 4,
      "curveTo": "{0.8934859589834695, 0.68017354289456433}",
      "hasCurveFrom": false,
      "hasCurveTo": true,
      "point": "{0.91051610487243839, 0.70073460322883729}"
    },
    {
      "_class": "curvePoint",
      "cornerRadius": 0,
      "curveFrom": "{1.0047144955022207, 0.81433435522371822}",
      "curveMode": 4,
      "curveTo": "{0.9906069779984723, 0.79743600694741024}",
      "hasCurveFrom": true,
      "hasCurveTo": false,
      "point": "{0.9906069779984723, 0.79743600694741024}"
    },
    {
      "_class": "curvePoint",
      "cornerRadius": 0,
      "curveFrom": "{0.9859623927560266, 0.85266649582870646}",
      "curveMode": 4,
      "curveTo": "{1.0027418104573482, 0.83779228607218981}",
      "hasCurveFrom": false,
      "hasCurveTo": true,
      "point": "{0.9859623927560266, 0.85266649582870646}"
    }
  ],
  "resizingConstraint": 63,
  "resizingType": 0,
  "rotation": 0,
  "shouldBreakMaskChain": false,
  "style": {
    "_class": "style",
    "do_objectID": "ABF3EB0E-F4AD-47D7-BE5A-BDF80BDBBD73",
    "endMarkerType": 0,
    "fills": [
      {
        "_class": "fill",
        "color": {
          "_class": "color",
          "alpha": 1,
          "blue": 0,
          "green": 0,
          "red": 0
        },
        "fillType": 0,
        "isEnabled": true,
        "noiseIndex": 0,
        "noiseIntensity": 0,
        "patternFillType": 1,
        "patternTileScale": 1
      }
    ],
    "miterLimit": 10,
    "startMarkerType": 0,
    "windingRule": 0
  }
}